bibtex_file_mcp.py
bibtex_file_mcp-1.1.0.dist-info/METADATA
bibtex_file_mcp-1.1.0.dist-info/WHEEL
bibtex_file_mcp-1.1.0.dist-info/entry_points.txt
bibtex_file_mcp-1.1.0.dist-info/top_level.txt
bibtex_file_mcp-1.1.0.dist-info/RECORD
