Metadata-Version: 2.4
Name: bibtex-file-mcp
Version: 1.1.0
Summary: BibTeX MCP Server for manipulating BibTeX entries
Author-email: Qing <aqsz2526@outlook.com>
Maintainer-email: Qing <aqsz2@outlook.com>
License-Expression: MIT
Project-URL: Homepage, https://github.com/Qing25/bibtex-file-mcp
Project-URL: Repository, https://github.com/Qing25/bibtex-file-mcp.git
Project-URL: Issues, https://github.com/Qing25/bibtex-file-mcp/issues
Project-URL: Documentation, https://github.com/Qing25/bibtex-file-mcp#readme
Keywords: bibtex,mcp,bibliography,reference-management,citation,latex
Classifier: Development Status :: 4 - Beta
Classifier: Intended Audience :: Developers
Classifier: Intended Audience :: Science/Research
Classifier: Programming Language :: Python :: 3.10
Classifier: Programming Language :: Python :: 3.11
Classifier: Programming Language :: Python :: 3.12
Classifier: Topic :: Scientific/Engineering
Classifier: Topic :: Text Processing
Classifier: Operating System :: OS Independent
Requires-Python: >=3.10
Requires-Dist: mcp>=0.1.0
Requires-Dist: fastmcp>=0.1.0
Requires-Dist: pydantic>=2.0.0
